[
  {
    "id": 1,
    "title": "Reliable Solution",
    "description": "A highly secure, scalable and convenient wallets solution that will provide you with peace of mind."
  },
  {
    "id": 2,
    "title": "Leading Gateway",
    "description": "Accept cryptocurrency payments easily and securely with one of the industry’s leading cryptocurrency gateway."
  },
  {
    "id": 3,
    "title": "Favorable Rates",
    "description": "Receive cryptocurrencies and convert it into stablecoins with good rates."
  },
  {
    "id": 4,
    "title": "Crypto Withdrawals",
    "description": "Conveniently withdraw cryptos to your blockchain wallet."
  }
]
